experiment/__init__.py
experiment/appenv.py
experiment/rewrite-rules.json
experiment/settings.py
experiment/test.py
experiment/cli/__init__.py
experiment/cli/api.py
experiment/cli/configuration.py
experiment/cli/context.py
experiment/cli/exit_codes.py
experiment/cli/git.py
experiment/cli/login.py
experiment/cli/package.py
experiment/cli/pull_secrets.py
experiment/cli/pvep_schema.jsonschema
experiment/cli/stack.py
experiment/cli/stp.py
experiment/model/__init__.py
experiment/model/codes.py
experiment/model/conf.py
experiment/model/data.py
experiment/model/errors.py
experiment/model/executors.py
experiment/model/graph.py
experiment/model/interface.py
experiment/model/storage.py
experiment/model/frontends/__init__.py
experiment/model/frontends/cwl.py
experiment/model/frontends/dosini.py
experiment/model/frontends/dsl.py
experiment/model/frontends/flowir.py
experiment/model/hooks/__init__.py
experiment/model/hooks/hooks.py
experiment/model/hooks/interface.py
experiment/model/hooks/utils.py
experiment/resources/Template.package.tar
experiment/runtime/__init__.py
experiment/runtime/backends.py
experiment/runtime/backends_base.py
experiment/runtime/control.py
experiment/runtime/engine.py
experiment/runtime/errors.py
experiment/runtime/monitor.py
experiment/runtime/optimizer.py
experiment/runtime/output.py
experiment/runtime/span.py
experiment/runtime/status.py
experiment/runtime/task.py
experiment/runtime/workflow.py
experiment/runtime/backend_interfaces/__init__.py
experiment/runtime/backend_interfaces/docker.py
experiment/runtime/backend_interfaces/k8s.py
experiment/runtime/backend_interfaces/localtask.py
experiment/runtime/backend_interfaces/lsf.py
experiment/runtime/backend_interfaces/stage-out.sh
experiment/runtime/backend_interfaces/task_simulator.py
experiment/runtime/interpreters/__init__.py
experiment/runtime/interpreters/cwl.py
experiment/runtime/interpreters/cwl_cmdline.py
experiment/runtime/interpreters/js.py
experiment/runtime/utilities/__init__.py
st4sd_runtime_core-2.5.1.dist-info/licenses/LICENSE.md
st4sd_runtime_core-2.5.1.dist-info/METADATA
st4sd_runtime_core-2.5.1.dist-info/WHEEL
st4sd_runtime_core-2.5.1.dist-info/top_level.txt
st4sd_runtime_core-2.5.1.dist-info/RECORD
