Metadata-Version: 2.4
Name: st4sd-runtime-core
Version: 2.5.1
Summary: A tool for creating and deploying computational experiments
Home-page: https://github.com/st4sd/st4sd-runtime-core
Author: Michael A. Johnston
Author-email: michaelj@ie.ibm.com
License: Apache 2.0
Keywords: hpc kubernetes openshift lsf workflows experiments computational-chemistry simulation science
Classifier: Development Status :: 4 - Beta
Classifier: Intended Audience :: Developers
Classifier: Topic :: Software Development :: Build Tools
Classifier: Programming Language :: Python :: 3.8
Classifier: Programming Language :: Python :: 3.9
Classifier: Programming Language :: Python :: 3.10
License-File: LICENSE.md
Requires-Dist: reactivex>=4.0.0
Requires-Dist: pyyaml
Requires-Dist: pytest
Requires-Dist: pytest-xdist
Requires-Dist: pytest-timeout
Requires-Dist: networkx
Requires-Dist: matplotlib
Requires-Dist: requests
Requires-Dist: six
Requires-Dist: kubernetes
Requires-Dist: psutil
Requires-Dist: boto3>=1.36.0
Requires-Dist: pyrsistent
Requires-Dist: pymongo>=4.0
Requires-Dist: papermill
Requires-Dist: pandas
Requires-Dist: future
Requires-Dist: pydantic>=2.0.0
Requires-Dist: pydantic-settings
Requires-Dist: keyring
Requires-Dist: typer>=0.12.3
Requires-Dist: jsonschema
Provides-Extra: deploy
Requires-Dist: jupyter; extra == "deploy"
Requires-Dist: paho-mqtt; extra == "deploy"
Provides-Extra: develop
Requires-Dist: jupyter; extra == "develop"
Requires-Dist: paho-mqtt; extra == "develop"
Dynamic: author
Dynamic: author-email
Dynamic: classifier
Dynamic: description
Dynamic: description-content-type
Dynamic: home-page
Dynamic: keywords
Dynamic: license
Dynamic: license-file
Dynamic: provides-extra
Dynamic: requires-dist
Dynamic: summary
